setup.py
pydaag/__init__.py
pydaag/pydaag.py
pydaag/rotate.py
pydaag.egg-info/PKG-INFO
pydaag.egg-info/SOURCES.txt
pydaag.egg-info/dependency_links.txt
pydaag.egg-info/requires.txt
pydaag.egg-info/top_level.txt
pydaag.egg-info/zip-safe