Metadata-Version: 1.1
Name: pydaag
Version: 0.0.1
Summary: python image data augmentation
Home-page: https://github.com/taoyizhi68/py-data-augmentation
Author: Yizhi Tao
Author-email: see github
License: MIT
Platform: UNKNOWN
Classifier: License :: OSI Approved :: MIT License
Classifier: Programming Language :: Python :: 2.7
Classifier: Intended Audience :: Developers
Classifier: Operating System :: OS Independent
